nd2file/__init__.py
nd2file/nd2file.py
nd2file-0.0.1.dev2.dist-info/LICENSE
nd2file-0.0.1.dev2.dist-info/METADATA
nd2file-0.0.1.dev2.dist-info/WHEEL
nd2file-0.0.1.dev2.dist-info/top_level.txt
nd2file-0.0.1.dev2.dist-info/RECORD
