Metadata-Version: 2.1
Name: nd2file
Version: 0.0.1.dev2
Summary: Access Nikon NIS-Elements ND2 files
Home-page: https://github.com/csachs/nd2file
Author: Christian C. Sachs
Author-email: sachs.christian@gmail.com
License: BSD
Platform: UNKNOWN
Classifier: Development Status :: 4 - Beta
Classifier: License :: OSI Approved :: BSD License
Classifier: Programming Language :: Python :: 3
Requires: numpy
